{
    "type": "FeatureCollection",
    "features": [
        {
            "type": "Feature",
            "geometry": {
                "type": "Point",
                "coordinates": [
                    149.08406066800012,
                    -36.23199844399994
                ]
            },
            "properties": {
                "feedType": "incident",
                "sourceTitle": "DRY PLAINS RD, DAIRYMANS PLAINS",
                "category": "fire",
                "subcategory": "grass fire",
                "status": "under control",
                "id": "https://incidents.rfs.nsw.gov.au/api/v1/incidents/553487",
                "created": "2024-06-11T04:14:00+10:00",
                "updated": "2024-06-11T14:14:00+10:00",
                "location": "DRY PLAINS RD, DAIRYMANS PLAINS 2630",
                "size": 0,
                "description": "ALERT LEVEL: Advice <br />LOCATION: DRY PLAINS RD, DAIRYMANS PLAINS 2630 <br />COUNCIL AREA: Snowy Monaro <br />STATUS: Under control <br />TYPE: Grass Fire <br />FIRE: Yes <br />SIZE: 0 ha <br />RESPONSIBLE AGENCY: Rural Fire Service <br />UPDATED: 11 Jun 2024 14:14",
                "title": "incident: fire"
            }
        },
        {
            "type": "Feature",
            "geometry": {
                "type": "Point",
                "coordinates": [
                    149.0464496610001,
                    -35.47517499999998
                ]
            },
            "properties": {
                "feedType": "incident",
                "sourceTitle": "Lambrigg",
                "category": "fire",
                "subcategory": "grass fire",
                "status": "under control",
                "id": "https://incidents.rfs.nsw.gov.au/api/v1/incidents/553499",
                "created": "2024-06-11T05:49:00+10:00",
                "updated": "2024-06-11T15:49:00+10:00",
                "location": "LAMBRIGG 1163 TIDBINBILLA RD, PADDYS RIVER ACT 2620",
                "size": 0,
                "description": "ALERT LEVEL: Advice <br />LOCATION: LAMBRIGG 1163 TIDBINBILLA RD, PADDYS RIVER ACT 2620 <br />COUNCIL AREA: ACT <br />STATUS: Under control <br />TYPE: Grass Fire <br />FIRE: Yes <br />SIZE: 0 ha <br />RESPONSIBLE AGENCY: ACT Rural Fire Service <br />UPDATED: 11 Jun 2024 15:49",
                "title": "incident: fire"
            }
        },
        {
            "type": "Feature",
            "geometry": {
                "type": "Point",
                "coordinates": [
                    150.6450998780001,
                    -34.02531214099997
                ]
            },
            "properties": {
                "feedType": "incident",
                "sourceTitle": "B/Hill private hazard reduction",
                "category": "fire",
                "subcategory": "hazard reduction",
                "status": "under control",
                "id": "https://incidents.rfs.nsw.gov.au/api/v1/incidents/553414",
                "created": "2024-06-10T03:25:00+10:00",
                "updated": "2024-06-10T13:25:00+10:00",
                "location": "217 BROWNLOW HILL LOOP RD, BROWNLOW HILL NSW 2570",
                "size": 1,
                "description": "ALERT LEVEL: Planned Burn <br />LOCATION: 217 BROWNLOW HILL LOOP RD, BROWNLOW HILL NSW 2570 <br />COUNCIL AREA: Wollondilly <br />STATUS: Under control <br />TYPE: Hazard Reduction <br />FIRE: Yes <br />SIZE: 1 ha <br />RESPONSIBLE AGENCY: Rural Fire Service <br />UPDATED: 10 Jun 2024 13:25",
                "title": "incident: fire"
            }
        },
        {
            "type": "Feature",
            "geometry": {
                "type": "Point",
                "coordinates": [
                    149.29767608600002,
                    -29.25285598599993
                ]
            },
            "properties": {
                "feedType": "incident",
                "sourceTitle": "Emu HR",
                "category": "fire",
                "subcategory": "hazard reduction",
                "status": "under control",
                "id": "https://incidents.rfs.nsw.gov.au/api/v1/incidents/553490",
                "created": "2024-06-11T03:50:00+10:00",
                "updated": "2024-06-11T13:50:00+10:00",
                "location": "BUNNOR 5028 WATERCOURSE RD, MOREE NSW 2400",
                "size": 223,
                "description": "ALERT LEVEL: Planned Burn <br />LOCATION: BUNNOR 5028 WATERCOURSE RD, MOREE NSW 2400 <br />COUNCIL AREA: Moree Plains <br />STATUS: Under control <br />TYPE: Hazard Reduction <br />FIRE: Yes <br />SIZE: 223 ha <br />RESPONSIBLE AGENCY: NSW National Parks and Wildlife Service <br />UPDATED: 11 Jun 2024 13:50",
                "title": "incident: fire"
            }
        },
        {
            "type": "Feature",
            "geometry": {
                "type": "Point",
                "coordinates": [
                    149.3041992190001,
                    -29.24986054799996
                ]
            },
            "properties": {
                "feedType": "incident",
                "sourceTitle": "Emu HR",
                "category": "fire",
                "subcategory": "hazard reduction",
                "status": "under control",
                "id": "https://incidents.rfs.nsw.gov.au/api/v1/incidents/553491",
                "created": "2024-06-11T03:32:00+10:00",
                "updated": "2024-06-11T13:32:00+10:00",
                "location": "BUNNOR 5028 WATERCOURSE RD, MOREE NSW 2400",
                "size": 223,
                "description": "ALERT LEVEL: Planned Burn <br />LOCATION: BUNNOR 5028 WATERCOURSE RD, MOREE NSW 2400 <br />COUNCIL AREA: Moree Plains <br />STATUS: Under control <br />TYPE: Hazard Reduction <br />FIRE: Yes <br />SIZE: 223 ha <br />RESPONSIBLE AGENCY: NSW National Parks and Wildlife Service <br />UPDATED: 11 Jun 2024 13:32",
                "title": "incident: fire"
            }
        },
        {
            "type": "Feature",
            "geometry": {
                "type": "Point",
                "coordinates": [
                    148.9936523440001,
                    -33.33178329399993
                ]
            },
            "properties": {
                "feedType": "incident",
                "sourceTitle": "MOUNT CANOBOLAS RD",
                "category": "fire",
                "subcategory": "hazard reduction",
                "status": "under control",
                "id": "https://incidents.rfs.nsw.gov.au/api/v1/incidents/550333",
                "created": "2024-06-09T20:06:00+10:00",
                "updated": "2024-06-10T06:06:00+10:00",
                "location": "FINNERANS BLUFF 1606 MOUNT CANOBOLAS RD, CANOBOLAS 2800",
                "size": 0,
                "description": "ALERT LEVEL: Planned Burn <br />LOCATION: FINNERANS BLUFF 1606 MOUNT CANOBOLAS RD, CANOBOLAS 2800 <br />COUNCIL AREA: Cabonne <br />STATUS: Under control <br />TYPE: Hazard Reduction <br />FIRE: Yes <br />SIZE: 0 ha <br />RESPONSIBLE AGENCY: Rural Fire Service <br />UPDATED: 10 Jun 2024 06:06",
                "title": "incident: fire"
            }
        },
        {
            "type": "Feature",
            "geometry": {
                "type": "Point",
                "coordinates": [
                    150.12873840300006,
                    -35.81530380299995
                ]
            },
            "properties": {
                "feedType": "incident",
                "sourceTitle": "BIMBIMBIE RD, BIMBIMBIE",
                "category": "other",
                "subcategory": "planned event",
                "status": "under control",
                "id": "https://incidents.rfs.nsw.gov.au/api/v1/incidents/553481",
                "created": "2024-06-11T01:44:00+10:00",
                "updated": "2024-06-11T11:44:00+10:00",
                "location": "BIMBIMBIE RD, BIMBIMBIE 2536",
                "size": 0,
                "description": "ALERT LEVEL: Not Applicable <br />LOCATION: BIMBIMBIE RD, BIMBIMBIE 2536 <br />COUNCIL AREA: Eurobodalla <br />STATUS: Under control <br />TYPE: Planned Event <br />FIRE: No <br />SIZE: 0 ha <br />RESPONSIBLE AGENCY: Rural Fire Service <br />UPDATED: 11 Jun 2024 11:44",
                "title": "incident: other"
            }
        },
        {
            "type": "Feature",
            "geometry": {
                "type": "Point",
                "coordinates": [
                    148.46202087400002,
                    -29.050519943999973
                ]
            },
            "properties": {
                "feedType": "incident",
                "sourceTitle": "BOORA RD, COLLARENEBRI",
                "category": "fire",
                "subcategory": "structure fire",
                "status": "under control",
                "id": "https://incidents.rfs.nsw.gov.au/api/v1/incidents/553413",
                "created": "2024-06-11T03:20:00+10:00",
                "updated": "2024-06-11T13:20:00+10:00",
                "location": "JOMARA 2172 BOORA RD, COLLARENEBRI 2833",
                "size": 0,
                "description": "ALERT LEVEL: Not Applicable <br />LOCATION: JOMARA 2172 BOORA RD, COLLARENEBRI 2833 <br />COUNCIL AREA: Walgett <br />STATUS: Under control <br />TYPE: Structure Fire <br />FIRE: Yes <br />SIZE: 0 ha <br />RESPONSIBLE AGENCY: Rural Fire Service <br />UPDATED: 11 Jun 2024 13:20",
                "title": "incident: fire"
            }
        },
        {
            "type": "Feature",
            "geometry": {
                "type": "Point",
                "coordinates": [
                    150.1291351320001,
                    -34.66461563099995
                ]
            },
            "properties": {
                "feedType": "incident",
                "sourceTitle": "MURRIMBA RD, WINGELLO",
                "category": "other",
                "subcategory": "flood/storm/tree down",
                "status": "out of control",
                "id": "https://incidents.rfs.nsw.gov.au/api/v1/incidents/553513",
                "created": "2024-06-11T08:37:00+10:00",
                "updated": "2024-06-11T18:37:00+10:00",
                "location": "MURRIMBA RD, WINGELLO 2579",
                "size": 0,
                "description": "ALERT LEVEL: Not Applicable <br />LOCATION: MURRIMBA RD, WINGELLO 2579 <br />COUNCIL AREA: Wingecarribee <br />STATUS: Out of control <br />TYPE: Flood/Storm/Tree Down <br />FIRE: No <br />SIZE: 0 ha <br />RESPONSIBLE AGENCY: Rural Fire Service <br />UPDATED: 11 Jun 2024 18:37",
                "title": "incident: other"
            }
        },
        {
            "type": "Feature",
            "geometry": {
                "type": "Point",
                "coordinates": [
                    150.41186523400006,
                    -35.248901366999974
                ]
            },
            "properties": {
                "feedType": "incident",
                "sourceTitle": "SKYE FARM LANE, YATTE YATTAH",
                "category": "other",
                "subcategory": "flood/storm/tree down",
                "status": "being controlled",
                "id": "https://incidents.rfs.nsw.gov.au/api/v1/incidents/553510",
                "created": "2024-06-11T08:07:00+10:00",
                "updated": "2024-06-11T18:07:00+10:00",
                "location": "33A SKYE FARM LANE, YATTE YATTAH 2539",
                "size": 0,
                "description": "ALERT LEVEL: Not Applicable <br />LOCATION: 33A SKYE FARM LANE, YATTE YATTAH 2539 <br />COUNCIL AREA: Shoalhaven <br />STATUS: Being controlled <br />TYPE: Flood/Storm/Tree Down <br />FIRE: No <br />SIZE: 0 ha <br />RESPONSIBLE AGENCY: Rural Fire Service <br />UPDATED: 11 Jun 2024 18:07",
                "title": "incident: other"
            }
        },
        {
            "type": "Feature",
            "geometry": {
                "type": "Point",
                "coordinates": [
                    151.15502929600007,
                    -32.91904449499998
                ]
            },
            "properties": {
                "feedType": "incident",
                "sourceTitle": "WOLLOMBI RD, NARONE CREEK",
                "category": "other",
                "subcategory": "mva/transport",
                "status": "out of control",
                "id": "https://incidents.rfs.nsw.gov.au/api/v1/incidents/553500",
                "created": "2024-06-11T06:22:00+10:00",
                "updated": "2024-06-11T16:22:00+10:00",
                "location": "YELLOW BILLY 2609 WOLLOMBI RD, NARONE CREEK 2325",
                "size": 0,
                "description": "ALERT LEVEL: Not Applicable <br />LOCATION: YELLOW BILLY 2609 WOLLOMBI RD, NARONE CREEK 2325 <br />COUNCIL AREA: Cessnock <br />STATUS: Out of control <br />TYPE: MVA/Transport <br />FIRE: No <br />SIZE: 0 ha <br />RESPONSIBLE AGENCY: Rural Fire Service <br />UPDATED: 11 Jun 2024 16:22",
                "title": "incident: other"
            }
        },
        {
            "type": "Feature",
            "geometry": {
                "type": "Point",
                "coordinates": [
                    150.73342895500002,
                    -34.60313034099994
                ]
            },
            "properties": {
                "feedType": "incident",
                "sourceTitle": "YELLOW ROCK RD, YELLOW ROCK",
                "category": "fire",
                "subcategory": "structure fire",
                "status": "under control",
                "id": "https://incidents.rfs.nsw.gov.au/api/v1/incidents/553498",
                "created": "2024-06-11T07:09:00+10:00",
                "updated": "2024-06-11T17:09:00+10:00",
                "location": "347 YELLOW ROCK RD, YELLOW ROCK 2527",
                "size": 0,
                "description": "ALERT LEVEL: Not Applicable <br />LOCATION: 347 YELLOW ROCK RD, YELLOW ROCK 2527 <br />COUNCIL AREA: Shellharbour <br />STATUS: Under control <br />TYPE: Structure Fire <br />FIRE: Yes <br />SIZE: 0 ha <br />RESPONSIBLE AGENCY: Rural Fire Service <br />UPDATED: 11 Jun 2024 17:09",
                "title": "incident: fire"
            }
        }
    ]
}