{
    "type": "FeatureCollection",
    "features": [
        {
            "type": "Feature",
            "geometry": {
                "type": "Point",
                "coordinates": [
                    151.30671501200004,
                    -33.041790499999934
                ]
            },
            "properties": {
                "feedType": "incident",
                "sourceTitle": "Forestry Watagans Crayfish Windrow",
                "category": "fire",
                "subcategory": "hazard reduction",
                "status": "under control",
                "id": "https://incidents.rfs.nsw.gov.au/api/v1/incidents/462661",
                "created": "2022-08-12T21:55:00+10:00",
                "updated": "2022-08-13T07:55:00+10:00",
                "location": "15km west of Morisset",
                "size": 45,
                "description": "ALERT LEVEL: Advice <br />LOCATION: 15km west of Morisset  <br />COUNCIL AREA: Cessnock <br />STATUS: Under control <br />TYPE: Hazard Reduction <br />FIRE: Yes <br />SIZE: 45 ha <br />RESPONSIBLE AGENCY: Forestry Corporation of NSW <br />UPDATED: 13 Aug 2022 07:55",
                "title": "incident: fire"
            }
        },
        {
            "type": "Feature",
            "geometry": {
                "type": "Point",
                "coordinates": [
                    152.56371975100012,
                    -29.54603229099996
                ]
            },
            "properties": {
                "feedType": "incident",
                "sourceTitle": "Grange Plantation HRB",
                "category": "fire",
                "subcategory": "hazard reduction",
                "status": "under control",
                "id": "https://incidents.rfs.nsw.gov.au/api/v1/incidents/461924",
                "created": "2022-08-12T22:31:00+10:00",
                "updated": "2022-08-13T08:31:00+10:00",
                "location": "grange access road",
                "size": 20,
                "description": "ALERT LEVEL: Advice <br />LOCATION: grange access road <br />COUNCIL AREA: Clarence Valley <br />STATUS: Under control <br />TYPE: Hazard Reduction <br />FIRE: Yes <br />SIZE: 20 ha <br />RESPONSIBLE AGENCY: Forestry Corporation of NSW <br />UPDATED: 13 Aug 2022 08:31",
                "title": "incident: fire"
            }
        },
        {
            "type": "Feature",
            "geometry": {
                "type": "Point",
                "coordinates": [
                    153.05255413100008,
                    -31.063962904999983
                ]
            },
            "properties": {
                "feedType": "incident",
                "sourceTitle": "Hat Head Village South HR",
                "category": "fire",
                "subcategory": "hazard reduction",
                "status": "under control",
                "id": "https://incidents.rfs.nsw.gov.au/api/v1/incidents/462761",
                "created": "2022-08-12T23:49:00+10:00",
                "updated": "2022-08-13T09:49:00+10:00",
                "location": "marlin circuit hat head",
                "size": 24,
                "description": "ALERT LEVEL: Advice <br />LOCATION: marlin circuit hat head <br />COUNCIL AREA: Kempsey <br />STATUS: Under control <br />TYPE: Hazard Reduction <br />FIRE: Yes <br />SIZE: 24 ha <br />RESPONSIBLE AGENCY: NSW National Parks and Wildlife Service <br />UPDATED: 13 Aug 2022 09:49",
                "title": "incident: fire"
            }
        },
        {
            "type": "Feature",
            "geometry": {
                "type": "Point",
                "coordinates": [
                    150.87832900000012,
                    -34.367100999999934
                ]
            },
            "properties": {
                "feedType": "incident",
                "sourceTitle": "Lower Escarpment Firetrail, Corrimal",
                "category": "fire",
                "subcategory": "bushfire",
                "status": "out of control",
                "id": "https://incidents.rfs.nsw.gov.au/api/v1/incidents/463002",
                "created": "2022-08-13T05:20:00+10:00",
                "updated": "2022-08-13T15:20:00+10:00",
                "location": "Lower Escarpment Firetrail, Corrimal, NSW 2518",
                "size": 0,
                "description": "ALERT LEVEL: Advice <br />LOCATION: Lower Escarpment Firetrail, Corrimal, NSW 2518 <br />COUNCIL AREA: Wollongong <br />STATUS: Out of control <br />TYPE: Bush Fire <br />FIRE: Yes <br />SIZE: 0 ha <br />RESPONSIBLE AGENCY: Rural Fire Service <br />UPDATED: 13 Aug 2022 15:20",
                "title": "incident: fire"
            }
        },
        {
            "type": "Feature",
            "geometry": {
                "type": "Point",
                "coordinates": [
                    151.5723180770001,
                    -32.77304946399994
                ]
            },
            "properties": {
                "feedType": "incident",
                "sourceTitle": "Assist DPI - Biosecurity Response (Varroa Mite)",
                "category": "other",
                "subcategory": "assist other agency",
                "status": "under control",
                "id": "https://incidents.rfs.nsw.gov.au/api/v1/incidents/457367",
                "created": "2022-08-13T01:00:00+10:00",
                "updated": "2022-08-13T11:00:00+10:00",
                "location": "110 Mount Vincent Road East Maitland",
                "size": 0,
                "description": "ALERT LEVEL: Not Applicable <br />LOCATION: 110 Mount Vincent Road East Maitland <br />COUNCIL AREA: Maitland <br />STATUS: Under control <br />TYPE: Assist Other Agency <br />FIRE: No <br />SIZE: 0 ha <br />RESPONSIBLE AGENCY: Rural Fire Service <br />UPDATED: 13 Aug 2022 11:00",
                "title": "incident: other"
            }
        },
        {
            "type": "Feature",
            "geometry": {
                "type": "Point",
                "coordinates": [
                    150.4729890000001,
                    -34.80230799999998
                ]
            },
            "properties": {
                "feedType": "incident",
                "sourceTitle": "Bugong Rd, Budgong",
                "category": "fire",
                "subcategory": "burn off",
                "status": "under control",
                "id": "https://incidents.rfs.nsw.gov.au/api/v1/incidents/462992",
                "created": "2022-08-13T01:06:00+10:00",
                "updated": "2022-08-13T11:06:00+10:00",
                "location": "760 Bugong Rd, Budgong, NSW 2577",
                "size": 0,
                "description": "ALERT LEVEL: Not Applicable <br />LOCATION: 760 Bugong Rd, Budgong, NSW 2577 <br />COUNCIL AREA: Shoalhaven <br />STATUS: Under control <br />TYPE: Burn off <br />FIRE: Yes <br />SIZE: 0 ha <br />RESPONSIBLE AGENCY: Rural Fire Service <br />UPDATED: 13 Aug 2022 11:06",
                "title": "incident: fire"
            }
        },
        {
            "type": "Feature",
            "geometry": {
                "type": "Point",
                "coordinates": [
                    149.00106300000004,
                    -33.306588999999974
                ]
            },
            "properties": {
                "feedType": "incident",
                "sourceTitle": "Cargo Rd, Nashdale",
                "category": "fire",
                "subcategory": "structure fire",
                "status": "under control",
                "id": "https://incidents.rfs.nsw.gov.au/api/v1/incidents/462978",
                "created": "2022-08-12T23:46:00+10:00",
                "updated": "2022-08-13T09:46:00+10:00",
                "location": "801 Cargo Rd, Nashdale, NSW 2800",
                "size": 0,
                "description": "ALERT LEVEL: Not Applicable <br />LOCATION: 801 Cargo Rd, Nashdale, NSW 2800 <br />COUNCIL AREA: Cabonne <br />STATUS: Under control <br />TYPE: Structure Fire <br />FIRE: Yes <br />SIZE: 0 ha <br />RESPONSIBLE AGENCY: Rural Fire Service <br />UPDATED: 13 Aug 2022 09:46",
                "title": "incident: fire"
            }
        },
        {
            "type": "Feature",
            "geometry": {
                "type": "Point",
                "coordinates": [
                    146.90505299900008,
                    -35.951175999999975
                ]
            },
            "properties": {
                "feedType": "incident",
                "sourceTitle": "Dights Forest Rd, Jindera",
                "category": "fire",
                "subcategory": "burn off",
                "status": "under control",
                "id": "https://incidents.rfs.nsw.gov.au/api/v1/incidents/462797",
                "created": "2022-08-13T04:44:00+10:00",
                "updated": "2022-08-13T14:44:00+10:00",
                "location": "Dights Forest Rd, Jindera, NSW 2642",
                "size": 0,
                "description": "ALERT LEVEL: Not Applicable <br />LOCATION: Dights Forest Rd, Jindera, NSW 2642 <br />COUNCIL AREA: Greater Hume <br />STATUS: Under control <br />TYPE: Burn off <br />FIRE: Yes <br />SIZE: 0 ha <br />RESPONSIBLE AGENCY: Rural Fire Service <br />UPDATED: 13 Aug 2022 14:44",
                "title": "incident: fire"
            }
        },
        {
            "type": "Feature",
            "geometry": {
                "type": "Point",
                "coordinates": [
                    150.45904500000006,
                    -34.775260999999944
                ]
            },
            "properties": {
                "feedType": "incident",
                "sourceTitle": "Duffys Lane, Budgong",
                "category": "fire",
                "subcategory": "burn off",
                "status": "under control",
                "id": "https://incidents.rfs.nsw.gov.au/api/v1/incidents/462985",
                "created": "2022-08-13T00:38:00+10:00",
                "updated": "2022-08-13T10:38:00+10:00",
                "location": "60 Duffys Lane, Budgong, NSW 2577",
                "size": 0,
                "description": "ALERT LEVEL: Not Applicable <br />LOCATION: 60 Duffys Lane, Budgong, NSW 2577 <br />COUNCIL AREA: Shoalhaven <br />STATUS: Under control <br />TYPE: Burn off <br />FIRE: Yes <br />SIZE: 0 ha <br />RESPONSIBLE AGENCY: Rural Fire Service <br />UPDATED: 13 Aug 2022 10:38",
                "title": "incident: fire"
            }
        },
        {
            "type": "Feature",
            "geometry": {
                "type": "Point",
                "coordinates": [
                    152.70932000000005,
                    -31.63325199999997
                ]
            },
            "properties": {
                "feedType": "incident",
                "sourceTitle": "Kendall Rd, Kendall",
                "category": "other",
                "subcategory": "mva/transport",
                "status": "under control",
                "id": "https://incidents.rfs.nsw.gov.au/api/v1/incidents/462996",
                "created": "2022-08-13T04:25:00+10:00",
                "updated": "2022-08-13T14:25:00+10:00",
                "location": "Kendall Rd, Kendall, NSW 2439",
                "size": 0,
                "description": "ALERT LEVEL: Not Applicable <br />LOCATION: Kendall Rd, Kendall, NSW 2439 <br />COUNCIL AREA: Port Macquarie-Hastings <br />STATUS: Under control <br />TYPE: MVA/Transport <br />FIRE: No <br />SIZE: 0 ha <br />RESPONSIBLE AGENCY: Rural Fire Service <br />UPDATED: 13 Aug 2022 14:25",
                "title": "incident: other"
            }
        },
        {
            "type": "Feature",
            "geometry": {
                "type": "Point",
                "coordinates": [
                    151.32084700000007,
                    -32.655438999999944
                ]
            },
            "properties": {
                "feedType": "incident",
                "sourceTitle": "New England Hwy, Lower Belford",
                "category": "other",
                "subcategory": "mva/transport",
                "status": "out of control",
                "id": "https://incidents.rfs.nsw.gov.au/api/v1/incidents/462988",
                "created": "2022-08-12T23:48:00+10:00",
                "updated": "2022-08-13T09:48:00+10:00",
                "location": "New England Hwy, Lower Belford, NSW 2335",
                "size": 0,
                "description": "ALERT LEVEL: Not Applicable <br />LOCATION: New England Hwy, Lower Belford, NSW 2335 <br />COUNCIL AREA: Singleton <br />STATUS: Out of control <br />TYPE: MVA/Transport <br />FIRE: No <br />SIZE: 0 ha <br />RESPONSIBLE AGENCY: Rural Fire Service <br />UPDATED: 13 Aug 2022 09:48",
                "title": "incident: other"
            }
        },
        {
            "type": "Feature",
            "geometry": {
                "type": "Point",
                "coordinates": [
                    150.97918600000003,
                    -33.65550899999994
                ]
            },
            "properties": {
                "feedType": "incident",
                "sourceTitle": "Pitt Town Rd, Kenthurst",
                "category": "fire",
                "subcategory": "other",
                "status": "out of control",
                "id": "https://incidents.rfs.nsw.gov.au/api/v1/incidents/462997",
                "created": "2022-08-13T03:42:00+10:00",
                "updated": "2022-08-13T13:42:00+10:00",
                "location": "68A Pitt Town Rd, Kenthurst, NSW 2156",
                "size": 0,
                "description": "ALERT LEVEL: Not Applicable <br />LOCATION: 68A Pitt Town Rd, Kenthurst, NSW 2156 <br />COUNCIL AREA: The Hills <br />STATUS: Out of control <br />TYPE: Other <br />FIRE: Yes <br />SIZE: 0 ha <br />RESPONSIBLE AGENCY: Rural Fire Service <br />UPDATED: 13 Aug 2022 13:42",
                "title": "incident: fire"
            }
        },
        {
            "type": "Feature",
            "geometry": {
                "type": "Point",
                "coordinates": [
                    150.70739300000002,
                    -33.55917499999998
                ]
            },
            "properties": {
                "feedType": "incident",
                "sourceTitle": "Slopes Rd, North Richmond",
                "category": "fire",
                "subcategory": "other",
                "status": "out of control",
                "id": "https://incidents.rfs.nsw.gov.au/api/v1/incidents/462999",
                "created": "2022-08-13T04:58:00+10:00",
                "updated": "2022-08-13T14:58:00+10:00",
                "location": "177 Slopes Rd, North Richmond, NSW 2754",
                "size": 0,
                "description": "ALERT LEVEL: Not Applicable <br />LOCATION: 177 Slopes Rd, North Richmond, NSW 2754 <br />COUNCIL AREA: Hawkesbury <br />STATUS: Out of control <br />TYPE: Other <br />FIRE: Yes <br />SIZE: 0 ha <br />RESPONSIBLE AGENCY: Rural Fire Service <br />UPDATED: 13 Aug 2022 14:58",
                "title": "incident: fire"
            }
        }
    ]
}