{
    "type": "FeatureCollection",
    "features": [
        {
            "type": "Feature",
            "geometry": {
                "type": "Point",
                "coordinates": [
                    137.982522128756,
                    -32.9652909949638,
                    0
                ]
            },
            "properties": {
                "feedType": "incident",
                "sourceTitle": "AUGUSTA HIGHWAY, PORT GERMEIN",
                "category": "vehicle",
                "subcategory": "vehicle accident",
                "status": "going",
                "id": "1545729",
                "created": "2023-09-05T08:32:00+09:30",
                "updated": "2023-09-05T08:32:00+09:30",
                "title": "incident: vehicle"
            },
            "id": "1545729"
        },
        {
            "type": "Feature",
            "geometry": {
                "type": "Point",
                "coordinates": [
                    138.673094755125,
                    -34.9530037688639,
                    0
                ]
            },
            "properties": {
                "feedType": "incident",
                "sourceTitle": "WATERFALL GULLY ROAD, WATERFALL GULLY",
                "category": "other",
                "subcategory": "assist agency",
                "status": "complete",
                "id": "1545728",
                "created": "2023-09-05T08:22:00+09:30",
                "updated": "2023-09-05T08:22:00+09:30",
                "title": "incident: other"
            },
            "id": "1545728"
        }
    ]
}