{
    "type": "FeatureCollection",
    "features": [
        {
            "type": "Feature",
            "geometry": {
                "type": "Point",
                "coordinates": [
                    138.722768507743,
                    -34.7639918457135,
                    0
                ]
            },
            "properties": {
                "feedType": "incident",
                "sourceTitle": "REUBEN RICHARDSON RD/LITTLE PARA ST , GREENWITH",
                "category": "other",
                "subcategory": "tree down",
                "status": "going",
                "id": "1619113",
                "created": "2024-12-26T17:16:00+10:30",
                "updated": "2024-12-26T17:16:00+10:30",
                "title": "incident: other"
            },
            "id": "1619113"
        }
    ]
}