{
    "type": "FeatureCollection",
    "features": [
        {
            "type": "Feature",
            "geometry": {
                "type": "Point",
                "coordinates": [
                    138.531833656972,
                    -34.9096782311523,
                    0
                ]
            },
            "properties": {
                "feedType": "incident",
                "sourceTitle": "FINDON ROAD, KIDMAN PARK",
                "category": "other",
                "subcategory": "fire alarm",
                "status": "going",
                "id": "1627816",
                "created": "2025-02-20T13:59:00+10:30",
                "updated": "2025-02-20T13:59:00+10:30",
                "title": "incident: other"
            },
            "id": "1627816"
        },
        {
            "type": "Feature",
            "geometry": {
                "type": "Point",
                "coordinates": [
                    138.645053324698,
                    -34.8927424701904,
                    0
                ]
            },
            "properties": {
                "feedType": "incident",
                "sourceTitle": "BRIAR ROAD, FELIXSTOW",
                "category": "other",
                "subcategory": "fire alarm",
                "status": "going",
                "id": "1627815",
                "created": "2025-02-20T13:43:00+10:30",
                "updated": "2025-02-20T13:43:00+10:30",
                "title": "incident: other"
            },
            "id": "1627815"
        },
        {
            "type": "Feature",
            "geometry": {
                "type": "Point",
                "coordinates": [
                    138.604497623083,
                    -34.9289231757782,
                    0
                ]
            },
            "properties": {
                "feedType": "incident",
                "sourceTitle": "WAKEFIELD STREET, ADELAIDE",
                "category": "other",
                "subcategory": "cover assignment",
                "status": "going",
                "id": "1625387",
                "created": "2025-02-06T12:45:00+10:30",
                "updated": "2025-02-06T12:45:00+10:30",
                "title": "incident: other"
            },
            "id": "1625387"
        }
    ]
}