{
    "type": "FeatureCollection",
    "features": [
        {
            "type": "Feature",
            "geometry": {
                "type": "Point",
                "sm_coordinates": "no",
                "coordinates": [
                    116.00575,
                    -32.028233
                ]
            },
            "properties": {
                "feedType": "incident",
                "sourceTitle": "ORANGE GROVE",
                "category": "fire",
                "subcategory": "burn off",
                "status": "active",
                "id": "2172370-541879",
                "created": "2021-09-28T09:03:59+08:00",
                "updated": "2021-09-28T09:03:59+08:00",
                "location": "ORANGE GROVE",
                "size": "",
                "description": "Burn Off",
                "title": "incident: fire"
            }
        },
        {
            "type": "Feature",
            "geometry": {
                "type": "Point",
                "sm_coordinates": "no",
                "coordinates": [
                    115.905,
                    -32.111526
                ]
            },
            "properties": {
                "feedType": "incident",
                "sourceTitle": "TREEBY",
                "category": "fire",
                "subcategory": "burn off",
                "status": "active",
                "id": "2172320-541847",
                "created": "2021-09-28T06:45:50+08:00",
                "updated": "2021-09-28T06:45:50+08:00",
                "location": "TREEBY",
                "size": "",
                "description": "Burn Off",
                "title": "incident: fire"
            }
        },
        {
            "type": "Feature",
            "geometry": {
                "type": "Point",
                "sm_coordinates": "no",
                "coordinates": [
                    115.53175,
                    -31.08307
                ]
            },
            "properties": {
                "feedType": "incident",
                "sourceTitle": "COWALLA",
                "category": "fire",
                "subcategory": "burn off",
                "status": "active",
                "id": "2172485-541933",
                "created": "2021-09-28T13:42:12+08:00",
                "updated": "2021-09-28T13:42:12+08:00",
                "location": "COWALLA",
                "size": "",
                "description": "Burn Off",
                "title": "incident: fire"
            }
        },
        {
            "type": "Feature",
            "geometry": {
                "type": "Point",
                "sm_coordinates": "no",
                "coordinates": [
                    115.54189,
                    -31.291452
                ]
            },
            "properties": {
                "feedType": "incident",
                "sourceTitle": "GABBADAH",
                "category": "fire",
                "subcategory": "burn off",
                "status": "active",
                "id": "2172555-541970",
                "created": "2021-09-28T15:52:39+08:00",
                "updated": "2021-09-28T15:52:39+08:00",
                "location": "GABBADAH",
                "size": "",
                "description": "Burn Off",
                "title": "incident: fire"
            }
        },
        {
            "type": "Feature",
            "geometry": {
                "type": "Point",
                "sm_coordinates": "no",
                "coordinates": [
                    126.385,
                    -18.88
                ]
            },
            "properties": {
                "feedType": "incident",
                "sourceTitle": "MUELLER RANGES",
                "category": "fire",
                "subcategory": "bushfire",
                "status": "monitoring",
                "id": "2171265-541115",
                "created": "2021-09-24T16:43:02+08:00",
                "updated": "2021-09-25T18:11:17+08:00",
                "location": "MUELLER RANGES",
                "size": "",
                "description": "Bushfire",
                "title": "incident: fire"
            }
        },
        {
            "type": "Feature",
            "geometry": {
                "type": "Point",
                "sm_coordinates": "no",
                "coordinates": [
                    115.91347,
                    -32.11495
                ]
            },
            "properties": {
                "feedType": "incident",
                "sourceTitle": "TREEBY",
                "category": "fire",
                "subcategory": "burn off",
                "status": "active",
                "id": "2172598-542004",
                "created": "2021-09-28T17:39:04+08:00",
                "updated": "2021-09-28T17:39:04+08:00",
                "location": "TREEBY",
                "size": "",
                "description": "Burn Off",
                "title": "incident: fire"
            }
        },
        {
            "type": "Feature",
            "geometry": {
                "type": "Point",
                "sm_coordinates": "no",
                "coordinates": [
                    115.6674,
                    -32.772808
                ]
            },
            "properties": {
                "feedType": "incident",
                "sourceTitle": "HERRON",
                "category": "fire",
                "subcategory": "burn off",
                "status": "active",
                "id": "2172331-541854",
                "created": "2021-09-28T07:45:18+08:00",
                "updated": "2021-09-28T07:45:18+08:00",
                "location": "HERRON",
                "size": "",
                "description": "Burn Off",
                "title": "incident: fire"
            }
        },
        {
            "type": "Feature",
            "geometry": {
                "type": "Point",
                "sm_coordinates": "no",
                "coordinates": [
                    126.71211,
                    -18.70858
                ]
            },
            "properties": {
                "feedType": "incident",
                "sourceTitle": "MUELLER RANGES",
                "category": "fire",
                "subcategory": "bushfire",
                "status": "monitoring",
                "id": "2171976-541662",
                "created": "2021-09-26T20:33:59+08:00",
                "updated": "2021-09-28T09:23:09+08:00",
                "location": "MUELLER RANGES",
                "size": "",
                "description": "Bushfire",
                "title": "incident: fire"
            }
        },
        {
            "type": "Feature",
            "geometry": {
                "type": "Point",
                "sm_coordinates": "no",
                "coordinates": [
                    122.17,
                    -17.37
                ]
            },
            "properties": {
                "feedType": "incident",
                "sourceTitle": "WATERBANK",
                "category": "fire",
                "subcategory": "bushfire",
                "status": "monitoring",
                "id": "2165603-538368",
                "created": "2021-09-05T11:52:47+08:00",
                "updated": "2021-09-25T18:10:36+08:00",
                "location": "WATERBANK",
                "size": "",
                "description": "Bushfire",
                "title": "incident: fire"
            }
        },
        {
            "type": "Feature",
            "geometry": {
                "type": "Point",
                "sm_coordinates": "no",
                "coordinates": [
                    115.63936,
                    -33.404316
                ]
            },
            "properties": {
                "feedType": "incident",
                "sourceTitle": "GELORUP",
                "category": "fire",
                "subcategory": "burn off",
                "status": "active",
                "id": "2172337-541859",
                "created": "2021-09-28T08:02:58+08:00",
                "updated": "2021-09-28T08:02:58+08:00",
                "location": "GELORUP",
                "size": "",
                "description": "Burn Off",
                "title": "incident: fire"
            }
        },
        {
            "type": "Feature",
            "geometry": {
                "type": "Point",
                "sm_coordinates": "no",
                "coordinates": [
                    115.18979,
                    -33.75168
                ]
            },
            "properties": {
                "feedType": "incident",
                "sourceTitle": "KALOORUP",
                "category": "fire",
                "subcategory": "burn off",
                "status": "active",
                "id": "2170306-540616",
                "created": "2021-09-22T07:59:32+08:00",
                "updated": "2021-09-22T09:26:05+08:00",
                "location": "KALOORUP",
                "size": "",
                "description": "Burn Off",
                "title": "incident: fire"
            }
        },
        {
            "type": "Feature",
            "geometry": {
                "type": "Point",
                "sm_coordinates": "no",
                "coordinates": [
                    116.073,
                    -31.557156
                ]
            },
            "properties": {
                "feedType": "incident",
                "sourceTitle": "LOWER CHITTERING",
                "category": "fire",
                "subcategory": "burn off",
                "status": "active",
                "id": "2172564-541977",
                "created": "2021-09-28T16:12:16+08:00",
                "updated": "2021-09-28T16:12:16+08:00",
                "location": "LOWER CHITTERING",
                "size": "",
                "description": "Burn Off",
                "title": "incident: fire"
            }
        },
        {
            "type": "Feature",
            "geometry": {
                "type": "Point",
                "sm_coordinates": "no",
                "coordinates": [
                    115.87458,
                    -32.2376
                ]
            },
            "properties": {
                "feedType": "incident",
                "sourceTitle": "CASUARINA",
                "category": "fire",
                "subcategory": "burn off",
                "status": "active",
                "id": "2172603-542008",
                "created": "2021-09-28T18:04:37+08:00",
                "updated": "2021-09-28T18:04:37+08:00",
                "location": "CASUARINA",
                "size": "",
                "description": "Burn Off",
                "title": "incident: fire"
            }
        },
        {
            "type": "Feature",
            "geometry": {
                "type": "Point",
                "sm_coordinates": "no",
                "coordinates": [
                    125.80998,
                    -28.343817
                ]
            },
            "properties": {
                "feedType": "incident",
                "sourceTitle": "BEADELL",
                "category": "fire",
                "subcategory": "bushfire",
                "status": "monitoring",
                "id": "2171031-541000",
                "created": "2021-09-24T08:31:04+08:00",
                "updated": "2021-09-26T07:08:31+08:00",
                "location": "BEADELL",
                "size": "",
                "description": "Bushfire",
                "title": "incident: fire"
            }
        },
        {
            "type": "Feature",
            "geometry": {
                "type": "Point",
                "sm_coordinates": "no",
                "coordinates": [
                    116.15644,
                    -31.360271
                ]
            },
            "properties": {
                "feedType": "incident",
                "sourceTitle": "BINDOON",
                "category": "fire",
                "subcategory": "burn off",
                "status": "active",
                "id": "2172373-541882",
                "created": "2021-09-28T09:07:31+08:00",
                "updated": "2021-09-28T09:07:31+08:00",
                "location": "BINDOON",
                "size": "",
                "description": "Burn Off",
                "title": "incident: fire"
            }
        },
        {
            "type": "Feature",
            "geometry": {
                "type": "Point",
                "sm_coordinates": "no",
                "coordinates": [
                    116.060715,
                    -32.118126
                ]
            },
            "properties": {
                "feedType": "incident",
                "sourceTitle": "ROLEYSTONE",
                "category": "fire",
                "subcategory": "burn off",
                "status": "active",
                "id": "2172621-542022",
                "created": "2021-09-28T19:46:20+08:00",
                "updated": "2021-09-28T19:46:20+08:00",
                "location": "ROLEYSTONE",
                "size": "",
                "description": "Burn Off",
                "title": "incident: fire"
            }
        },
        {
            "type": "Feature",
            "geometry": {
                "type": "Point",
                "sm_coordinates": "no",
                "coordinates": [
                    116.23556,
                    -31.786278
                ]
            },
            "properties": {
                "feedType": "incident",
                "sourceTitle": "GIDGEGANNUP",
                "category": "fire",
                "subcategory": "burn off",
                "status": "active",
                "id": "2172489-541936",
                "created": "2021-09-28T13:49:51+08:00",
                "updated": "2021-09-28T13:49:51+08:00",
                "location": "GIDGEGANNUP",
                "size": "",
                "description": "Burn Off",
                "title": "incident: fire"
            }
        },
        {
            "type": "Feature",
            "geometry": {
                "type": "Point",
                "sm_coordinates": "no",
                "coordinates": [
                    122.32,
                    -17.1
                ]
            },
            "properties": {
                "feedType": "incident",
                "sourceTitle": "DAMPIER PENINSULA",
                "category": "fire",
                "subcategory": "bushfire",
                "status": "monitoring",
                "id": "2165560-538331",
                "created": "2021-09-05T08:34:37+08:00",
                "updated": "2021-09-25T14:41:32+08:00",
                "location": "DAMPIER PENINSULA",
                "size": "",
                "description": "Bushfire",
                "title": "incident: fire"
            }
        },
        {
            "type": "Feature",
            "geometry": {
                "type": "Point",
                "sm_coordinates": "no",
                "coordinates": [
                    115.012,
                    -23.292
                ]
            },
            "properties": {
                "feedType": "incident",
                "sourceTitle": "YANNARIE",
                "category": "fire",
                "subcategory": "bushfire",
                "status": "monitoring",
                "id": "2172015-541680",
                "created": "2021-09-27T07:37:55+08:00",
                "updated": "2021-09-28T09:23:52+08:00",
                "location": "YANNARIE",
                "size": "",
                "description": "Bushfire",
                "title": "incident: fire"
            }
        },
        {
            "type": "Feature",
            "geometry": {
                "type": "Point",
                "sm_coordinates": "no",
                "coordinates": [
                    116.29654,
                    -31.698223
                ]
            },
            "properties": {
                "feedType": "incident",
                "sourceTitle": "MORANGUP",
                "category": "fire",
                "subcategory": "burn off",
                "status": "active",
                "id": "2172458-541921",
                "created": "2021-09-28T12:38:38+08:00",
                "updated": "2021-09-28T12:38:38+08:00",
                "location": "MORANGUP",
                "size": "",
                "description": "Burn Off",
                "title": "incident: fire"
            }
        },
        {
            "type": "Feature",
            "geometry": {
                "type": "Point",
                "sm_coordinates": "no",
                "coordinates": [
                    125.70083,
                    -14.836983
                ]
            },
            "properties": {
                "feedType": "incident",
                "sourceTitle": "MITCHELL PLATEAU",
                "category": "fire",
                "subcategory": "bushfire",
                "status": "monitoring",
                "id": "2170893-540902",
                "created": "2021-09-23T15:29:39+08:00",
                "updated": "2021-09-23T15:33:59+08:00",
                "location": "MITCHELL PLATEAU",
                "size": "",
                "description": "Bushfire",
                "title": "incident: fire"
            }
        },
        {
            "type": "Feature",
            "geometry": {
                "type": "Point",
                "sm_coordinates": "no",
                "coordinates": [
                    116.16452,
                    -31.925892
                ]
            },
            "properties": {
                "feedType": "incident",
                "sourceTitle": "MUNDARING",
                "category": "fire",
                "subcategory": "burn off",
                "status": "active",
                "id": "2172532-541956",
                "created": "2021-09-28T15:13:32+08:00",
                "updated": "2021-09-28T15:44:04+08:00",
                "location": "MUNDARING",
                "size": "",
                "description": "Burn Off",
                "title": "incident: fire"
            }
        },
        {
            "type": "Feature",
            "geometry": {
                "type": "Point",
                "sm_coordinates": "no",
                "coordinates": [
                    123.129,
                    -16.94
                ]
            },
            "properties": {
                "feedType": "incident",
                "sourceTitle": "DAMPIER PENINSULA",
                "category": "fire",
                "subcategory": "bushfire",
                "status": "monitoring",
                "id": "2169982-540476",
                "created": "2021-09-21T10:27:45+08:00",
                "updated": "2021-09-25T18:11:01+08:00",
                "location": "DAMPIER PENINSULA",
                "size": "",
                "description": "Bushfire",
                "title": "incident: fire"
            }
        },
        {
            "type": "Feature",
            "geometry": {
                "type": "Point",
                "sm_coordinates": "no",
                "coordinates": [
                    115.69624,
                    -31.59063
                ]
            },
            "properties": {
                "feedType": "incident",
                "sourceTitle": "CARABOODA",
                "category": "fire",
                "subcategory": "burn off",
                "status": "active",
                "id": "2169968-540472",
                "created": "2021-09-21T09:54:27+08:00",
                "updated": "2021-09-21T18:39:44+08:00",
                "location": "CARABOODA",
                "size": "",
                "description": "Burn Off",
                "title": "incident: fire"
            }
        },
        {
            "type": "Feature",
            "geometry": {
                "type": "Point",
                "sm_coordinates": "no",
                "coordinates": [
                    116.049324,
                    -31.788332
                ]
            },
            "properties": {
                "feedType": "incident",
                "sourceTitle": "BRIGADOON",
                "category": "fire",
                "subcategory": "burn off",
                "status": "active",
                "id": "2172594-542001",
                "created": "2021-09-28T17:28:41+08:00",
                "updated": "2021-09-28T17:28:41+08:00",
                "location": "BRIGADOON",
                "size": "",
                "description": "Burn Off",
                "title": "incident: fire"
            }
        },
        {
            "type": "Feature",
            "geometry": {
                "type": "Point",
                "sm_coordinates": "no",
                "coordinates": [
                    115.74988,
                    -31.675417
                ]
            },
            "properties": {
                "feedType": "incident",
                "sourceTitle": "NEERABUP",
                "category": "fire",
                "subcategory": "burn off",
                "status": "active",
                "id": "2172581-541993",
                "created": "2021-09-28T16:46:47+08:00",
                "updated": "2021-09-28T16:46:47+08:00",
                "location": "NEERABUP",
                "size": "",
                "description": "Burn Off",
                "title": "incident: fire"
            }
        },
        {
            "type": "Feature",
            "geometry": {
                "type": "Point",
                "sm_coordinates": "no",
                "coordinates": [
                    127.69192,
                    -18.23966
                ]
            },
            "properties": {
                "feedType": "incident",
                "sourceTitle": "MCBEATH",
                "category": "fire",
                "subcategory": "bushfire",
                "status": "monitoring",
                "id": "2172562-541975",
                "created": "2021-09-28T16:11:40+08:00",
                "updated": "2021-09-28T19:33:17+08:00",
                "location": "MCBEATH",
                "size": "",
                "description": "Bushfire",
                "title": "incident: fire"
            }
        },
        {
            "type": "Feature",
            "geometry": {
                "type": "Point",
                "sm_coordinates": "no",
                "coordinates": [
                    120.19028,
                    -31.215279
                ]
            },
            "properties": {
                "feedType": "incident",
                "sourceTitle": "BOORABBIN",
                "category": "fire",
                "subcategory": "burn off",
                "status": "active",
                "id": "2172449-541919",
                "created": "2021-09-28T12:27:20+08:00",
                "updated": "2021-09-28T12:27:20+08:00",
                "location": "BOORABBIN",
                "size": "",
                "description": "Burn Off",
                "title": "incident: fire"
            }
        },
        {
            "type": "Feature",
            "geometry": {
                "type": "Point",
                "sm_coordinates": "no",
                "coordinates": [
                    116.23095,
                    -31.779573
                ]
            },
            "properties": {
                "feedType": "incident",
                "sourceTitle": "GIDGEGANNUP",
                "category": "fire",
                "subcategory": "burn off",
                "status": "active",
                "id": "2172542-541961",
                "created": "2021-09-28T15:28:53+08:00",
                "updated": "2021-09-28T15:28:53+08:00",
                "location": "GIDGEGANNUP",
                "size": "",
                "description": "Burn Off",
                "title": "incident: fire"
            }
        },
        {
            "type": "Feature",
            "geometry": {
                "type": "Point",
                "sm_coordinates": "no",
                "coordinates": [
                    116.06161,
                    -31.567205
                ]
            },
            "properties": {
                "feedType": "incident",
                "sourceTitle": "LOWER CHITTERING",
                "category": "fire",
                "subcategory": "burn off",
                "status": "active",
                "id": "2172463-541924",
                "created": "2021-09-28T12:46:36+08:00",
                "updated": "2021-09-28T22:13:03+08:00",
                "location": "LOWER CHITTERING",
                "size": "",
                "description": "Burn Off",
                "title": "incident: fire"
            }
        },
        {
            "type": "Feature",
            "geometry": {
                "type": "Point",
                "sm_coordinates": "no",
                "coordinates": [
                    115.06594,
                    -33.58335
                ]
            },
            "properties": {
                "feedType": "incident",
                "sourceTitle": "NATURALISTE",
                "category": "fire",
                "subcategory": "burn off",
                "status": "active",
                "id": "2172486-541934",
                "created": "2021-09-28T13:42:25+08:00",
                "updated": "2021-09-28T13:42:25+08:00",
                "location": "NATURALISTE",
                "size": "",
                "description": "Burn Off",
                "title": "incident: fire"
            }
        },
        {
            "type": "Feature",
            "geometry": {
                "type": "Point",
                "sm_coordinates": "no",
                "coordinates": [
                    115.97335,
                    -32.148144
                ]
            },
            "properties": {
                "feedType": "incident",
                "sourceTitle": "HAYNES",
                "category": "fire",
                "subcategory": "burn off",
                "status": "active",
                "id": "2172570-541982",
                "created": "2021-09-28T16:27:25+08:00",
                "updated": "2021-09-28T16:33:57+08:00",
                "location": "HAYNES",
                "size": "",
                "description": "Burn Off",
                "title": "incident: fire"
            }
        },
        {
            "type": "Feature",
            "geometry": {
                "type": "Point",
                "sm_coordinates": "no",
                "coordinates": [
                    115.55271,
                    -31.156347
                ]
            },
            "properties": {
                "feedType": "incident",
                "sourceTitle": "WANERIE",
                "category": "fire",
                "subcategory": "burn off",
                "status": "active",
                "id": "2172477-541930",
                "created": "2021-09-28T13:11:51+08:00",
                "updated": "2021-09-28T13:12:01+08:00",
                "location": "WANERIE",
                "size": "",
                "description": "Burn Off",
                "title": "incident: fire"
            }
        },
        {
            "type": "Feature",
            "geometry": {
                "type": "Point",
                "sm_coordinates": "no",
                "coordinates": [
                    115.784485,
                    -32.40562
                ]
            },
            "properties": {
                "feedType": "incident",
                "sourceTitle": "KARNUP",
                "category": "fire",
                "subcategory": "burn off",
                "status": "active",
                "id": "2172569-541981",
                "created": "2021-09-28T16:25:30+08:00",
                "updated": "2021-09-28T16:25:30+08:00",
                "location": "KARNUP",
                "size": "",
                "description": "Burn Off",
                "title": "incident: fire"
            }
        },
        {
            "type": "Feature",
            "geometry": {
                "type": "Point",
                "sm_coordinates": "no",
                "coordinates": [
                    115.82317,
                    -31.710741
                ]
            },
            "properties": {
                "feedType": "incident",
                "sourceTitle": "MARIGINIUP",
                "category": "fire",
                "subcategory": "burn off",
                "status": "active",
                "id": "2172551-541967",
                "created": "2021-09-28T15:45:03+08:00",
                "updated": "2021-09-28T15:45:03+08:00",
                "location": "MARIGINIUP",
                "size": "",
                "description": "Burn Off",
                "title": "incident: fire"
            }
        },
        {
            "type": "Feature",
            "geometry": {
                "type": "Point",
                "sm_coordinates": "no",
                "coordinates": [
                    116.15561,
                    -31.808231
                ]
            },
            "properties": {
                "feedType": "incident",
                "sourceTitle": "GIDGEGANNUP",
                "category": "fire",
                "subcategory": "burn off",
                "status": "active",
                "id": "2170791-540862",
                "created": "2021-09-23T11:44:09+08:00",
                "updated": "2021-09-28T15:48:14+08:00",
                "location": "GIDGEGANNUP",
                "size": "",
                "description": "Burn Off",
                "title": "incident: fire"
            }
        },
        {
            "type": "Feature",
            "geometry": {
                "type": "Point",
                "sm_coordinates": "no",
                "coordinates": [
                    115.04303,
                    -33.65745
                ]
            },
            "properties": {
                "feedType": "incident",
                "sourceTitle": "YALLINGUP",
                "category": "fire",
                "subcategory": "burn off",
                "status": "active",
                "id": "2172558-541972",
                "created": "2021-09-28T16:05:22+08:00",
                "updated": "2021-09-28T16:05:22+08:00",
                "location": "YALLINGUP",
                "size": "",
                "description": "Burn Off",
                "title": "incident: fire"
            }
        },
        {
            "type": "Feature",
            "geometry": {
                "type": "Point",
                "sm_coordinates": "no",
                "coordinates": [
                    118.24243,
                    -34.3681
                ]
            },
            "properties": {
                "feedType": "incident",
                "sourceTitle": "STIRLING RANGE NATIONAL PARK",
                "category": "incident",
                "subcategory": "incident",
                "status": "on scene",
                "id": "2172525-541938",
                "created": "2021-09-28T13:57:12+08:00",
                "updated": "2021-09-28T16:32:21+08:00",
                "location": "STIRLING RANGE NATIONAL PARK",
                "size": "",
                "description": "Incident",
                "title": "incident: incident"
            }
        },
        {
            "type": "Feature",
            "geometry": {
                "type": "Point",
                "sm_coordinates": "no",
                "coordinates": [
                    115.055626,
                    -33.650543
                ]
            },
            "properties": {
                "feedType": "incident",
                "sourceTitle": "YALLINGUP",
                "category": "fire",
                "subcategory": "burn off",
                "status": "active",
                "id": "2172534-541957",
                "created": "2021-09-28T15:15:20+08:00",
                "updated": "2021-09-28T15:15:20+08:00",
                "location": "YALLINGUP",
                "size": "",
                "description": "Burn Off",
                "title": "incident: fire"
            }
        },
        {
            "type": "Feature",
            "geometry": {
                "type": "Point",
                "sm_coordinates": "no",
                "coordinates": [
                    116.11535,
                    -31.62551
                ]
            },
            "properties": {
                "feedType": "incident",
                "sourceTitle": "BULLSBROOK",
                "category": "fire",
                "subcategory": "burn off",
                "status": "active",
                "id": "2172593-541999",
                "created": "2021-09-28T17:26:13+08:00",
                "updated": "2021-09-28T17:26:13+08:00",
                "location": "BULLSBROOK",
                "size": "",
                "description": "Burn Off",
                "title": "incident: fire"
            }
        },
        {
            "type": "Feature",
            "geometry": {
                "type": "Point",
                "sm_coordinates": "no",
                "coordinates": [
                    123.6978,
                    -17.39579
                ]
            },
            "properties": {
                "feedType": "incident",
                "sourceTitle": "DERBY",
                "category": "fire",
                "subcategory": "bushfire",
                "status": "on scene",
                "id": "2172605-542010",
                "created": "2021-09-28T18:19:51+08:00",
                "updated": "2021-09-28T21:06:45+08:00",
                "location": "DERBY",
                "size": "",
                "description": "Bushfire",
                "title": "incident: fire"
            }
        },
        {
            "type": "Feature",
            "geometry": {
                "type": "Point",
                "sm_coordinates": "no",
                "coordinates": [
                    118.29529,
                    -31.464573
                ]
            },
            "properties": {
                "feedType": "incident",
                "sourceTitle": "MERREDIN",
                "category": "fire",
                "subcategory": "burn off",
                "status": "active",
                "id": "2172540-541960",
                "created": "2021-09-28T15:24:53+08:00",
                "updated": "2021-09-28T15:25:16+08:00",
                "location": "MERREDIN",
                "size": "",
                "description": "Burn Off",
                "title": "incident: fire"
            }
        },
        {
            "type": "Feature",
            "geometry": {
                "type": "Point",
                "sm_coordinates": "no",
                "coordinates": [
                    115.789696,
                    -31.767456
                ]
            },
            "properties": {
                "feedType": "incident",
                "sourceTitle": "EDGEWATER",
                "category": "fire",
                "subcategory": "burn off",
                "status": "active",
                "id": "2172592-541998",
                "created": "2021-09-28T17:22:08+08:00",
                "updated": "2021-09-28T17:22:08+08:00",
                "location": "EDGEWATER",
                "size": "",
                "description": "Burn Off",
                "title": "incident: fire"
            }
        },
        {
            "type": "Feature",
            "geometry": {
                "type": "Point",
                "sm_coordinates": "no",
                "coordinates": [
                    116.069374,
                    -32.107147
                ]
            },
            "properties": {
                "feedType": "incident",
                "sourceTitle": "ROLEYSTONE",
                "category": "fire",
                "subcategory": "burn off",
                "status": "active",
                "id": "2172482-541931",
                "created": "2021-09-28T13:36:42+08:00",
                "updated": "2021-09-28T13:54:47+08:00",
                "location": "ROLEYSTONE",
                "size": "",
                "description": "Burn Off",
                "title": "incident: fire"
            }
        },
        {
            "type": "Feature",
            "geometry": {
                "type": "Point",
                "sm_coordinates": "no",
                "coordinates": [
                    115.93245,
                    -31.856222
                ]
            },
            "properties": {
                "feedType": "incident",
                "sourceTitle": "BENNETT SPRINGS",
                "category": "fire",
                "subcategory": "burn off",
                "status": "active",
                "id": "2172610-542014",
                "created": "2021-09-28T18:45:33+08:00",
                "updated": "2021-09-28T18:45:33+08:00",
                "location": "BENNETT SPRINGS",
                "size": "",
                "description": "Burn Off",
                "title": "incident: fire"
            }
        },
        {
            "type": "Feature",
            "geometry": {
                "type": "Point",
                "sm_coordinates": "no",
                "coordinates": [
                    120.538,
                    -23.387
                ]
            },
            "properties": {
                "feedType": "incident",
                "sourceTitle": "NEWMAN",
                "category": "fire",
                "subcategory": "bushfire",
                "status": "monitoring",
                "id": "2172550-541966",
                "created": "2021-09-28T15:40:11+08:00",
                "updated": "2021-09-28T15:42:51+08:00",
                "location": "NEWMAN",
                "size": "",
                "description": "Bushfire",
                "title": "incident: fire"
            }
        },
        {
            "type": "Feature",
            "geometry": {
                "type": "Point",
                "sm_coordinates": "no",
                "coordinates": [
                    116.05802,
                    -31.646006
                ]
            },
            "properties": {
                "feedType": "incident",
                "sourceTitle": "BULLSBROOK",
                "category": "fire",
                "subcategory": "burn off",
                "status": "active",
                "id": "2172629-542029",
                "created": "2021-09-28T20:39:48+08:00",
                "updated": "2021-09-28T20:39:48+08:00",
                "location": "BULLSBROOK",
                "size": "",
                "description": "Burn Off",
                "title": "incident: fire"
            }
        },
        {
            "type": "Feature",
            "geometry": {
                "type": "Point",
                "sm_coordinates": "no",
                "coordinates": [
                    116.23658,
                    -31.762526
                ]
            },
            "properties": {
                "feedType": "incident",
                "sourceTitle": "GIDGEGANNUP",
                "category": "fire",
                "subcategory": "burn off",
                "status": "active",
                "id": "2172526-541953",
                "created": "2021-09-28T15:05:48+08:00",
                "updated": "2021-09-28T15:05:48+08:00",
                "location": "GIDGEGANNUP",
                "size": "",
                "description": "Burn Off",
                "title": "incident: fire"
            }
        },
        {
            "type": "Feature",
            "geometry": {
                "type": "Point",
                "sm_coordinates": "no",
                "coordinates": [
                    115.87849,
                    -32.03873
                ]
            },
            "properties": {
                "feedType": "incident",
                "sourceTitle": "WILLETTON",
                "category": "fire",
                "subcategory": "burn off",
                "status": "active",
                "id": "2172606-542011",
                "created": "2021-09-28T18:27:50+08:00",
                "updated": "2021-09-28T18:39:01+08:00",
                "location": "WILLETTON",
                "size": "",
                "description": "Burn Off",
                "title": "incident: fire"
            }
        },
        {
            "type": "Feature",
            "geometry": {
                "type": "Point",
                "sm_coordinates": "no",
                "coordinates": [
                    115.03583,
                    -33.81334
                ]
            },
            "properties": {
                "feedType": "incident",
                "sourceTitle": "WILYABRUP",
                "category": "fire",
                "subcategory": "burn off",
                "status": "active",
                "id": "2172628-542028",
                "created": "2021-09-28T20:20:55+08:00",
                "updated": "2021-09-28T20:20:55+08:00",
                "location": "WILYABRUP",
                "size": "",
                "description": "Burn Off",
                "title": "incident: fire"
            }
        },
        {
            "type": "Feature",
            "geometry": {
                "type": "Point",
                "sm_coordinates": "no",
                "coordinates": [
                    119.16141,
                    -32.27684
                ]
            },
            "properties": {
                "feedType": "incident",
                "sourceTitle": "HYDEN",
                "category": "hazardous materials",
                "subcategory": "hazardous materials",
                "status": "monitoring",
                "id": "2172596-542000",
                "created": "2021-09-28T17:25:46+08:00",
                "updated": "2021-09-28T19:37:34+08:00",
                "location": "HYDEN",
                "size": "",
                "description": "Hazardous Materials",
                "title": "incident: hazardous materials"
            }
        }
    ]
}